exceptional/__init__.py
exceptional/exceptional.py
exceptional/py.typed
exceptional-24.1.0.dist-info/LICENSE.rst
exceptional-24.1.0.dist-info/METADATA
exceptional-24.1.0.dist-info/WHEEL
exceptional-24.1.0.dist-info/top_level.txt
exceptional-24.1.0.dist-info/RECORD
